LICENSE
readme.org
setup.cfg
setup.py
pyfresh/__init__.py
pyfresh/pyfresh.py
pyfresh/version.py
pyfresh.egg-info/PKG-INFO
pyfresh.egg-info/SOURCES.txt
pyfresh.egg-info/dependency_links.txt
pyfresh.egg-info/entry_points.txt
pyfresh.egg-info/top_level.txt