Metadata-Version: 1.1
Name: pyfresh
Version: 1.2
Summary: Recursively clean up python files in your projects.
Home-page: https://gitlab.com/python-open-source-library-collection/pyfresh
Author: Oliver Marks
Author-email: oly@digitaloctave.com
License:                     GNU GENERAL PUBLIC LICENSE
